<IODATA><PAGE action="load" option="extendedinfo" sessionkey="725C46575FB24DCDAD3422711F1B3DC8" dialoglanguageid="ENG" languagevariantid="ENU" guid="91D54C1E206A4358862AF67B280A0831" id="234" templateguid="99FF22F6B6F84A31BD1BE968F953C5AE" templaterights="2147483646" mainlinkguid="8CF1092FF9C348E5A4F5B5A4CD52B030" editlinkguid="8CF1092FF9C348E5A4F5B5A4CD52B030" parentguid="8CF1092FF9C348E5A4F5B5A4CD52B030" headline="FAQs - List of FAQs 234" name="" sitemapname="" templatepath="BodyContent" templatetitle="FAQs - List of FAQs" templateflags="536870912" headlinedescription="Headline (Title for this FAQ list)" status="1" flags="268960768" breadcrumbstartpoint="0" breadcrumbdonotuse="0" releaseguid="" createdate="41963.4089467593" createuserguid="AE1C1CF32B854C9FA30488508F0C3E15" createusername="broughtb" changedate="41963.4089583333" changeuserguid="AE1C1CF32B854C9FA30488508F0C3E15" changeusername="broughtb" releasedate="41963.4391435185" releaseusername="broughtb" releaseuserguid="AE1C1CF32B854C9FA30488508F0C3E15" lockdate="42013.608275463" lastchangesincelocked="42013.608275463" lockuserguid="AE1C1CF32B854C9FA30488508F0C3E15" lockusername="broughtb" lockuseremail="broughtb@otc.edu" checkindate="41963.4391435185" drafttemplates="0" templateswaitforrelease="0" templatelockuserguid="" templatelockdate="" templatelockusername="" templatelock="0" previousreleasedversionexists="1" useconnection="1" projectguid="F027326883D14209BF89C10ADD453837" userguid="E94BD09105A64CDDB94A0BA097958424" btflags="0"><ELEMENTS action="load" pageguid="91D54C1E206A4358862AF67B280A0831" parenttable="PAG" guid="91D54C1E206A4358862AF67B280A0831"><ELEMENT languagevariantid="ENU" defaultlanguagevariantid="" languageindependent="0" guid="7594C6358D7B4358BA10946A733AC18F" templateelementguid="57DFE936F77348F4B6EB79715718B040" pageguid="91D54C1E206A4358862AF67B280A0831" eltflags="0" flags="2097152" eltrequired="0" formularorderid="0" orderid="1" islink="0" name="stf_bodyClassIdentifier" eltname="stf_bodyClassIdentifier" aliasname="stf_bodyClassIdentifier" variable="stf_bodyClassIdentifier" type="1" elttype="1" templateelementflags="2097152" templateelementislink="0" value=""/><ELEMENT languagevariantid="ENU" defaultlanguagevariantid="" languageindependent="0" guid="619BE3384F284C67A0328B4D99EDA460" templateelementguid="27F9C45B946F43429DD404935CF81A25" pageguid="91D54C1E206A4358862AF67B280A0831" eltflags="0" flags="2228224" eltrequired="0" formularorderid="0" orderid="1" islink="0" name="stf_contentClassId" eltname="stf_contentClassId" aliasname="stf_contentClassId" variable="stf_contentClassId" type="1" elttype="1" templateelementflags="2228224" templateelementislink="0" value="" reddotdescription="Content Class Identifier"/><ELEMENT languagevariantid="ENU" defaultlanguagevariantid="" languageindependent="0" editoroptions="1717616536" guid="7358F7C0F91B4E82AAB19CBC591DC3B2" templateelementguid="5BFC7F2D58D24A29A992AA89E7C10E10" pageguid="91D54C1E206A4358862AF67B280A0831" eltflags="0" flags="0" eltrequired="0" formularorderid="0" orderid="1" islink="0" name="txt_faqDescription" eltname="txt_faqDescription" aliasname="txt_faqDescription" variable="txt_faqDescription" eltstylesheetdata="" type="32" elttype="32" templateelementflags="0" templateelementislink="0" value="" reddotdescription="A description paragraph for the list of FAQs"/><ELEMENT languagevariantid="ENU" defaultlanguagevariantid="" languageindependent="0" editoroptions="577551644" guid="43922B1D84524A39B64AA4DA29963BC0" templateelementguid="0465280072FF4349A0C8409A123E2354" pageguid="91D54C1E206A4358862AF67B280A0831" eltflags="0" flags="64" eltrequired="0" formularorderid="0" orderid="1" islink="0" name="txt_text" eltname="txt_text" aliasname="txt_text" variable="txt_text" eltstylesheetdata="&lt;STYLE&gt; &lt;/STYLE&gt;" type="32" elttype="32" templateelementflags="64" templateelementislink="0" value="" reddotdescription="Text content for page"/></ELEMENTS><LINKS action="load" pageguid="91D54C1E206A4358862AF67B280A0831" parenttable="PAG" guid="91D54C1E206A4358862AF67B280A0831"><LINK languagevariantid="ENU" defaultlanguagevariantid="" languageindependent="0" guid="6257A8AC467F4A499301D2197156B40B" templateelementguid="D7FBD22562D84519AA679741FB9BBDDF" pageguid="91D54C1E206A4358862AF67B280A0831" eltflags="0" flags="5242896" eltrequired="0" formularorderid="0" orderid="1" islink="2" name="list_faqs" eltname="list_faqs" aliasname="list_faqs" variable="list_faqs" type="13" elttype="13" templateelementflags="5242896" templateelementislink="2" value="list_faqs"/></LINKS><MAINLINK guid="8CF1092FF9C348E5A4F5B5A4CD52B030" name="con_body" pageguid="AAB05394A29341BEA0211A756ACD3B2B" pageheadline="Nice Sprites"/><PROJECTVARIANTS><PROJECTVARIANT guid="076101C773C646ED9F74A44455BB618A" name="HTML" checked="1"><TEMPLATEVARIANTS><TEMPLATEVARIANT guid="19217E5E52574F3FBE7D7A13B1E2EF7D" name="HTML" generatorstatustext="Will be published"/></TEMPLATEVARIANTS></PROJECTVARIANT><PROJECTVARIANT guid="78B00DC922B040168BE0F9D00038EF89" name="Mobile_Testing" checked="0"><TEMPLATEVARIANTS><TEMPLATEVARIANT guid="19217E5E52574F3FBE7D7A13B1E2EF7D" name="HTML" generatorstatustext="Will be published"/></TEMPLATEVARIANTS></PROJECTVARIANT><PROJECTVARIANT guid="B72FEA180FEF4E6DA6137E7727F73F47" name="testing" checked="0"><TEMPLATEVARIANTS><TEMPLATEVARIANT guid="19217E5E52574F3FBE7D7A13B1E2EF7D" name="HTML" generatorstatustext="Will be published"/></TEMPLATEVARIANTS></PROJECTVARIANT></PROJECTVARIANTS></PAGE>
</IODATA>